flawlessapi/__init__.py
flawlessapi/circuit_breaker.py
flawlessapi/connection_pool.py
flawlessapi/errors.py
flawlessapi/examples_of_Use.py
flawlessapi/main.py
flawlessapi/requests.py
flawlessapi/response.py
flawlessapi/cache/__init__.py
flawlessapi/cache/cache_test.py
flawlessapi/cache/factory.py
flawlessapi/cache/lru_cache.py
flawlessapi/cache/redis_cache.py
flawlessapi/config/__init__.py
flawlessapi/config/cache_config.py
flawlessapi/config/settings.py
flawlessapi/database/__init__.py
flawlessapi/database/manager.py
flawlessapi/distributed/__init__.py
flawlessapi/distributed/lock.py
flawlessapi/docs/__init__.py
flawlessapi/docs/auto_docs.py
flawlessapi/docs/generator.py
flawlessapi/handlers/__init__.py
flawlessapi/handlers/file_upload.py
flawlessapi/handlers/static.py
flawlessapi/handlers/websocket.py
flawlessapi/i18n/__init__.py
flawlessapi/i18n/translator.py
flawlessapi/logger/__init__.py
flawlessapi/logger/logger.py
flawlessapi/logs/__init__.py
flawlessapi/middleware/__init__.py
flawlessapi/middleware/base.py
flawlessapi/middleware/cors.py
flawlessapi/middleware/csrf.py
flawlessapi/middleware/rate_limit.py
flawlessapi/monitoring/__init__.py
flawlessapi/monitoring/metrics.py
flawlessapi/monitoring/monitoring.py
flawlessapi/monitoring/tracer.py
flawlessapi/plugins/__init__.py
flawlessapi/plugins/events.py
flawlessapi/router/__init__.py
flawlessapi/router/cache.py
flawlessapi/router/core.py
flawlessapi/router/decorators.py
flawlessapi/router/patterns.py
flawlessapi/security/__init__.py
flawlessapi/security/jwt.py
flawlessapi/security/validators.py
flawlessapi/security/xss.py
flawlessapi/service/__init__.py
flawlessapi/service/registry.py
flawlessapi/task_queue/__init__.py
flawlessapi/task_queue/task_queue.py
flawlessapi/tasks/__init__.py
flawlessapi/tasks/scheduler.py
flawlessapi/template/__init__.py
flawlessapi/template/engine.py
FlawlessAPI-0.3.0.dist-info/METADATA
FlawlessAPI-0.3.0.dist-info/WHEEL
FlawlessAPI-0.3.0.dist-info/top_level.txt
FlawlessAPI-0.3.0.dist-info/RECORD
