Metadata-Version: 2.1
Name: FlawlessAPI
Version: 0.3.0
Summary: 一个高性能的API服务框架
Author-email: wen <799771344@qq.com>
Project-URL: Homepage, https://github.com/799771344/FlawlessAPI
Project-URL: Bug Tracker, https://github.com/799771344/FlawlessAPI/issues
Classifier: Programming Language :: Python :: 3
Classifier: License :: OSI Approved :: MIT License
Classifier: Operating System :: OS Independent
Classifier: Framework :: AsyncIO
Requires-Python: >=3.9
Requires-Dist: uvicorn >=0.15.0
Requires-Dist: aiohttp >=3.8.0
Requires-Dist: pydantic >=1.8.0
Requires-Dist: jinja2 >=3.0.0
Requires-Dist: werkzeug >=2.0.0
Requires-Dist: aiofiles >=0.8.0
Requires-Dist: python-jose >=3.3.0
Requires-Dist: docstring-parser >=0.15
Requires-Dist: jwt >=1.3.1
Requires-Dist: aiocron >=1.8
Requires-Dist: databases >=0.9.0
Requires-Dist: sqlalchemy >=2.0.36
Requires-Dist: psutil >=6.1.0
